bqfetch/__init__.py
bqfetch/bqfetch.py
bqfetch/utils.py
bqfetch-1.1.0.dist-info/LICENSE
bqfetch-1.1.0.dist-info/METADATA
bqfetch-1.1.0.dist-info/WHEEL
bqfetch-1.1.0.dist-info/top_level.txt
bqfetch-1.1.0.dist-info/RECORD
