Metadata-Version: 2.1
Name: bqfetch
Version: 1.1.0
Summary: A tool to fetch tables from BigQuery as pandas DataFrames, fast.
Home-page: https://github.com/TristanBilot/bqfetch
Author: Tristan Bilot
Author-email: bilot.tristan@hotmail.fr
Classifier: Programming Language :: Python :: 3
Classifier: License :: OSI Approved :: MIT License
Classifier: Operating System :: OS Independent
Requires-Python: >=3.6
License-File: LICENSE
